progressivis/__init__.py
progressivis/_version.py
progressivis/py.typed
progressivis/cluster/__init__.py
progressivis/cluster/mb_k_means.py
progressivis/core/__init__.py
progressivis/core/aio.py
progressivis/core/api.py
progressivis/core/changemanager_base.py
progressivis/core/changemanager_dict.py
progressivis/core/changemanager_literal.py
progressivis/core/changemanager_pintset.py
progressivis/core/config.py
progressivis/core/dataflow.py
progressivis/core/decorators.py
progressivis/core/delta.py
progressivis/core/docstrings.py
progressivis/core/magics.py
progressivis/core/module.py
progressivis/core/module_facade.py
progressivis/core/pintset.py
progressivis/core/print.py
progressivis/core/pv_types.py
progressivis/core/quality.py
progressivis/core/scheduler.py
progressivis/core/settings.py
progressivis/core/sink.py
progressivis/core/slot.py
progressivis/core/slot_join.py
progressivis/core/storagemanager.py
progressivis/core/time_predictor.py
progressivis/core/tracer_base.py
progressivis/core/utils.py
progressivis/core/wait.py
progressivis/datasets/__init__.py
progressivis/datasets/random.py
progressivis/datasets/wget.py
progressivis/datashape/__init__.py
progressivis/datashape/__init__.pyi
progressivis/datashape/coretypes.py
progressivis/datashape/discovery.py
progressivis/datashape/dispatch.py
progressivis/datashape/error.py
progressivis/datashape/internal_utils.py
progressivis/datashape/lexer.py
progressivis/datashape/parser.py
progressivis/datashape/predicates.py
progressivis/datashape/promote.py
progressivis/datashape/py2help.py
progressivis/datashape/type_symbol_table.py
progressivis/datashape/typesets.py
progressivis/datashape/user.py
progressivis/datashape/validation.py
progressivis/datashape/util/__init__.py
progressivis/expr/__init__.py
progressivis/expr/core.py
progressivis/expr/io.py
progressivis/expr/select.py
progressivis/expr/stats.py
progressivis/expr/table.py
progressivis/io/__init__.py
progressivis/io/_threaded_read_csv.py
progressivis/io/api.py
progressivis-0.2.2.dist-info/METADATA
progressivis-0.2.2.dist-info/WHEEL
progressivis-0.2.2.dist-info/licenses/LICENSE
progressivis-0.2.2.dist-info/RECORD
