Metadata-Version: 2.4
Name: progressivis
Version: 0.2.2
Summary: A Progressive Steerable Analytics Toolkit
Project-URL: Homepage, https://github.com/progressivis/progressivis
Project-URL: Documentation, https://progressivis.readthedocs.io/en/latest/
Project-URL: Repository, https://github.com/progressivis/progressivis.git
Author-email: "INRIA, Jean-Daniel Fekete, Christian Poli" <jean-daniel.fekete@inria.fr>
License-Expression: BSD-2-Clause
License-File: LICENSE
Keywords: Progressive analytics visualization
Classifier: Intended Audience :: Developers
Classifier: Intended Audience :: Science/Research
Classifier: Programming Language :: Python
Classifier: Programming Language :: Python :: 3
Classifier: Programming Language :: Python :: 3.10
Classifier: Programming Language :: Python :: 3.11
Classifier: Programming Language :: Python :: 3.12
Classifier: Programming Language :: Python :: 3.13
Classifier: Topic :: Scientific/Engineering :: Information Analysis
Classifier: Topic :: Scientific/Engineering :: Visualization
Requires-Python: >=3.10
Requires-Dist: boto
Requires-Dist: datasketches
Requires-Dist: fast-histogram
Requires-Dist: multipledispatch>=0.4.7
Requires-Dist: numexpr>=2.6.1
Requires-Dist: numpy
Requires-Dist: pandas>=1.2.5
Requires-Dist: pillow>=4.2.0
Requires-Dist: pyarrow>=8.0.0
Requires-Dist: pyroaring
Requires-Dist: python-dateutil>=2.6.1
Requires-Dist: pyyaml>=5.4.1
Requires-Dist: requests
Requires-Dist: s3fs
Requires-Dist: scikit-learn>=1.0.0
Requires-Dist: scipy>=0.18.1
Requires-Dist: typeguard
Provides-Extra: docs
Requires-Dist: graphviz; extra == 'docs'
Requires-Dist: jinja2; extra == 'docs'
Requires-Dist: myst-parser>=0.18.1; extra == 'docs'
Requires-Dist: pydata-sphinx-theme>=0.12.0; extra == 'docs'
Requires-Dist: sphinx-autodoc-typehints>=1.20.0; extra == 'docs'
Requires-Dist: sphinx-gallery>=0.11.1; extra == 'docs'
Requires-Dist: sphinx<8; extra == 'docs'
Requires-Dist: sphinxcontrib-mermaid; extra == 'docs'
Requires-Dist: sphinxcontrib-napoleon>=0.7; extra == 'docs'
Requires-Dist: sphinxemoji; extra == 'docs'
Provides-Extra: jupyter
Requires-Dist: ipyprogressivis; extra == 'jupyter'
Provides-Extra: scripts
Requires-Dist: click; extra == 'scripts'
Provides-Extra: test
Requires-Dist: duckdb; extra == 'test'
Requires-Dist: pytest; extra == 'test'
Requires-Dist: pytest-cov; extra == 'test'
Requires-Dist: rangehttpserver; extra == 'test'
Provides-Extra: typing
Requires-Dist: duckdb; extra == 'typing'
Requires-Dist: ipython; extra == 'typing'
Requires-Dist: jinja2; extra == 'typing'
Requires-Dist: mypy>=1.0.1; extra == 'typing'
Requires-Dist: numpy; extra == 'typing'
Requires-Dist: pandas-stubs; extra == 'typing'
Requires-Dist: scipy-stubs; extra == 'typing'
Requires-Dist: sqlalchemy-stubs; extra == 'typing'
Requires-Dist: traits-stubs; extra == 'typing'
Requires-Dist: traittypes; extra == 'typing'
Requires-Dist: typeguard; extra == 'typing'
Requires-Dist: types-pillow; extra == 'typing'
Requires-Dist: types-pytz; extra == 'typing'
Requires-Dist: types-pyyaml; extra == 'typing'
Requires-Dist: types-requests; extra == 'typing'
Requires-Dist: types-setuptools; extra == 'typing'
Requires-Dist: types-urllib3; extra == 'typing'
Requires-Dist: typing-extensions; extra == 'typing'
